LICENSE
MANIFEST.in
README.rst
requirements.txt
setup.cfg
setup.py
chronograph/__init__.py
chronograph/chronograph.py
chronograph.egg-info/PKG-INFO
chronograph.egg-info/SOURCES.txt
chronograph.egg-info/dependency_links.txt
chronograph.egg-info/not-zip-safe
chronograph.egg-info/top_level.txt
chronograph/tests/__init__.py
chronograph/tests/test_chronograph.py
docs/Makefile
docs/chronograph.rst
docs/chronograph.tests.rst
docs/conf.py
docs/index.rst
docs/modules.rst
docs/_static/nature.css