Metadata-Version: 1.1
Name: chronograph
Version: 1.0.1
Summary: Chronograph is a simple stopwatch / chronometer / chronograph for timing Python code.
Home-page: https://github.com/computron/chronograph
Author: Anubhav Jain
Author-email: anubhavster@gmail.com
License: MIT
Platform: UNKNOWN
Classifier: Programming Language :: Python :: 2.7
Classifier: Development Status :: 4 - Beta
Classifier: Intended Audience :: Developers
Classifier: Operating System :: OS Independent
Classifier: Topic :: Utilities
